eeweather/__init__.py
eeweather/__version__.py
eeweather/access_api.py
eeweather/cache.py
eeweather/cli.py
eeweather/connections.py
eeweather/database.py
eeweather/exceptions.py
eeweather/geo.py
eeweather/mockable.py
eeweather/ranking.py
eeweather/stations.py
eeweather/summaries.py
eeweather/testing.py
eeweather/utils.py
eeweather/validation.py
eeweather/visualization.py
eeweather/warnings.py
eeweather/resources/GSOD-MISSING.op.gz
eeweather/resources/GSOD.op.gz
eeweather/resources/ISD-MISSING.gz
eeweather/resources/ISD-NAN.gz
eeweather/resources/ISD.gz
eeweather/resources/__init__.py
eeweather/resources/metadata.db
eeweather-0.3.30.dist-info/licenses/LICENSE
eeweather-0.3.30.dist-info/METADATA
eeweather-0.3.30.dist-info/WHEEL
eeweather-0.3.30.dist-info/entry_points.txt
eeweather-0.3.30.dist-info/top_level.txt
eeweather-0.3.30.dist-info/RECORD
