Metadata-Version: 2.4
Name: eeweather
Version: 0.3.30
Summary: Weather for Open Energy Efficiency Meter
Home-page: http://github.com/openeemeter/eeweather
Author: Phil Ngo
Author-email: phil@openee.io
License: Apache 2.0
Classifier: License :: OSI Approved :: Apache Software License
Classifier: Programming Language :: Python
Classifier: Programming Language :: Python :: 3
Classifier: Programming Language :: Python :: 3.4
Classifier: Programming Language :: Python :: 3.5
Classifier: Programming Language :: Python :: 3.6
License-File: LICENSE
Requires-Dist: click
Requires-Dist: pandas>=1.0.0
Requires-Dist: pyproj>=1.9.6
Requires-Dist: requests
Requires-Dist: shapely
Requires-Dist: retry
Dynamic: author
Dynamic: author-email
Dynamic: classifier
Dynamic: description
Dynamic: home-page
Dynamic: license
Dynamic: license-file
Dynamic: requires-dist
Dynamic: summary
